    {
        "type": "teacher_unavailable",
        "entity": {
            "type": "teacher",
            "teacher_id": "5a6b7c8d-9e0f-1a2b-3c4d-5e6f7a8b9c0d"
        },
        "conflict": {
            "requested_slot": {
                "start_time": "10:00",
                "end_time": "11:00",
                "day": "wednesday"
            }
        },
        "evidence": [
            {
                "teacher_id": "5a6b7c8d-9e0f-1a2b-3c4d-5e6f7a8b9c0d",
                "preferred_slots": [
                    {
                        "start_time": "08:00",
                        "end_time": "09:00",
                        "day": "wednesday"
                    },
                    {
                        "start_time": "12:00",
                        "end_time": "13:00",
                        "day": "wednesday"
                    }
                ]
            }
        ]
    }